aver/__init__.py
aver/networks/__init__.py
aver/networks/abstract.py
aver-0.1.0a1.dist-info/METADATA
aver-0.1.0a1.dist-info/RECORD
aver-0.1.0a1.dist-info/WHEEL
aver-0.1.0a1.dist-info/entry_points.txt
aver-0.1.0a1.dist-info/top_level.txt
fvf/__init__.py
fvf/__main__.py
fvf/model.py
fvf/munge.py
fvf/plot.py
fvf/simulator.py
