Metadata-Version: 2.1
Name: aver
Version: 0.1.0a1
Summary: Active Vision models, built with the Nengo neural simulator
Home-page: https://github.com/NickleDave/active-vision-nengo
Author: David Nicholson
Author-email: nicholdav@gmail.com
License: BSD
Platform: UNKNOWN
Classifier: License :: OSI Approved :: BSD License
Classifier: Programming Language :: Python
Classifier: Programming Language :: Python :: 3
Classifier: Programming Language :: Python :: 3.6
Classifier: Programming Language :: Python :: Implementation :: CPython
Requires-Python: >=3.6.0
Requires-Dist: numpy
Requires-Dist: scipy
Requires-Dist: matplotlib
Requires-Dist: jupyterlab
Requires-Dist: nengo
Requires-Dist: tqdm
